rail_tpu_utils/__init__.py
tpu_utils/__init__.py
tpu_utils/jax_utils.py
tpu_utils/networking.py
rail_tpu_utils-0.0.3.dist-info/LICENSE
rail_tpu_utils-0.0.3.dist-info/METADATA
rail_tpu_utils-0.0.3.dist-info/WHEEL
rail_tpu_utils-0.0.3.dist-info/top_level.txt
rail_tpu_utils-0.0.3.dist-info/RECORD
