Metadata-Version: 2.1
Name: rail_tpu_utils
Version: 0.0.3
Summary: Basic utilities for TPUs!
Author-email: Dibya Ghosh <dibya.ghosh@berkeley.edu>
Project-URL: Homepage, https://github.com/dibyaghosh/tpu_utils
Classifier: Programming Language :: Python :: 3
Classifier: License :: OSI Approved :: MIT License
Classifier: Operating System :: OS Independent
Requires-Python: >=3.8
License-File: LICENSE
Requires-Dist: requests
Requires-Dist: google-cloud-storage
